{
  "metadata": {
    "rows": 17,
    "cols": 16,
    "timestamp": 1763142228.008167,
    "version": "1.0",
    "winner": "circle",
    "final_scores": {
      "circle": 100.0,
      "square": 0.0
    },
    "game_duration": 190.83467936515808
  },
  "states": [
    "....................................................aaaaaaaa........aaaaaaaa.........................................................................................................................AAAAAAA........AAAAAAAA........A...........................................",
    "....................................................aaaaaaaa........aaaaabaa.........................................................................................................................AAAAAAA........AAAAAAAA........A...........................................",
    "....................................................aaaaaaaa........aaaaabaa.........................................................................................................................AAAAAAA........ABAAAAAA........A...........................................",
    "....................................................aaaaaaaa........aaaaabca.........................................................................................................................AAAAAAA........ABAAAAAA........A...........................................",
    "....................................................aaaaaaaa........aaaaabca.........................................................................................................................AAAAAAA....A....BAAAAAA........A...........................................",
    "....................................................aaaaaaac........aaaaabca.........................................................................................................................AAAAAAA....A....BAAAAAA........A...........................................",
    "....................................................aaaaaaac........aaaaabca.........................................................................................................................AAAAAA.....A....BAAAAAA........A......A....................................",
    "....................................................aaaaaaac.........aaaabca........a................................................................................................................AAAAAA.....A....BAAAAAA........A......A....................................",
    "....................................................aaaaaaac.........aaaabca........a................................................................................................................AAAAAA.....C....BAAAAAA........A......A....................................",
    "....................................................aaaaaaaa.........aaaabca........a................................................................................................................AAAAAA.....C....BAAAAAA........A......A....................................",
    "................................A...................aaaaaaaa.........aaaabca........a.................................................................................................................AAAAA.....C....BAAAAAA........A......A....................................",
    "................................A...................aaaaaaaa.........aaaacca........a.................................................................................................................AAAAA.....C....BAAAAAA........A......A....................................",
    ".................................A..................aaaaaaaa.........aaaacca........a.................................................................................................................AAAAA.....C....BAAAAAA........A......A....................................",
    ".................................A..................aaaaaaba.........aaaacca........a.................................................................................................................AAAAA.....C....BAAAAAA........A......A....................................",
    "..................................A.................aaaaaaba.........aaaacca........a.................................................................................................................AAAAA.....C....BAAAAAA........A......A....................................",
    "..................................A.................baaaaaba.........aaaacca........a.................................................................................................................AAAAA.....C....BAAAAAA........A......A....................................",
    "...................................A................baaaaaba.........aaaacca........a.................................................................................................................AAAAA.....C....BAAAAAA........A......A....................................",
    "...................................A................baaaaaba.........aaaaccb........a.................................................................................................................AAAAA.....C....BAAAAAA........A......A....................................",
    "....................................A...............baaaaaba.........aaaaccb........a.................................................................................................................AAAAA.....C....BAAAAAA........A......A....................................",
    "....................................A...............baaaabba.........aaaaccb........a.................................................................................................................AAAAA.....C....BAAAAAA........A......A....................................",
    ".....................................A..............baaaabba.........aaaaccb........a.................................................................................................................AAAAA.....C....BAAAAAA........A......A....................................",
    ".....................................A..............baaaabba.........acaaccb........a.................................................................................................................AAAAA.....C....BAAAAAA........A......A....................................",
    "................A....................A..............baaaabba.........acaaccb........a.................................................................................................................AAAAA.....C....B.AAAAA........A......A....................................",
    "................A....................A..............baaaabba.........acaaccc........a.................................................................................................................AAAAA.....C....B.AAAAA........A......A....................................",
    ".................A...................A..............baaaabba.........acaaccc........a.................................................................................................................AAAAA.....C....B.AAAAA........A......A....................................",
    ".................A...................A..............baaaabba.........aca.ccc........a...a.............................................................................................................AAAAA.....C....B.AAAAA........A......A....................................",
    "..................A..................A..............baaaabba.........aca.ccc........a...a.............................................................................................................AAAAA.....C....B.AAAAA........A......A....................................",
    "..................A..................A..............baaaabba.........aca.ccc........b...a.............................................................................................................AAAAA.....C....B.AAAAA........A......A....................................",
    "...................A.................A..............baaaabba.........aca.ccc........b...a.............................................................................................................AAAAA.....C....B.AAAAA........A......A....................................",
    "...................A.................A..............baaaaaba.........aca.ccc........b...a.............................................................................................................AAAAA.....C....B.AAAAA........A......A....................................",
    "....................A................A..............baaaaaba.........aca.ccc........b...a.............................................................................................................AAAAA.....C....B.AAAAA........A......A....................................",
    "....................A................A..............baaaaabb.........aca.ccc........b...a.............................................................................................................AAAAA.....C....B.AAAAA........A......A....................................",
    ".....................A...............A..............baaaaabb.........aca.ccc........b...a.............................................................................................................AAAAA.....C....B.AAAAA........A......A....................................",
    ".....................A...............A..............baaaaabb.........aca.ccc........b..a..............................................................................................................AAAAA.....C....B.AAAAA........A......A....................................",
    "......................A..............A..............baaaaabb.........aca.ccc........b..a..............................................................................................................AAAAA.....C....B.AAAAA........A......A....................................",
    "......................A..............A..............baaaaabb........a.ca.ccc........b..a..............................................................................................................AAAAA.....C....B.AAAAA........A......A....................................",
    ".....................................AA.............baaaaabb........a.ca.ccc........b..a..............................................................................................................AAAAA.....C....B.AAAAA........A......A....................................",
    ".....................................AA.............bcaaaabb........a.ca.ccc........b..a..............................................................................................................AAAAA.....C....B.AAAAA........A......A....................................",
    ".....................................AA.............bcaaaabb........a.ca.ccc........b..a..............................................................................................................AAAAA.....C...AB.AAAAA...............A....................................",
    ".....................................AA.............bcaaaabb........a.ca.ccc........b..................a..............................................................................................AAAAA.....C...AB.AAAAA...............A....................................",
    "................A....................AA.............bcaaaabb........a.ca.ccc........b..................a..............................................................................................AAAAA.....C....B.AAAAA...............A....................................",
    "................A....................AA.............bcaaaabb........a.ca.cbc........b..................a..............................................................................................AAAAA.....C....B.AAAAA...............A....................................",
    ".................A...................AA.............bcaaaabb........a.ca.cbc........b..................a..............................................................................................AAAAA.....C....B.AAAAA...............A....................................",
    ".................A...................AA.............bcaaaabb........a.ca.cbc........b..................c..............................................................................................AAAAA.....C....B.AAAAA...............A....................................",
    "..................A..................AA.............bcaaaabb........a.ca.cbc........b..................c..............................................................................................AAAAA.....C....B.AAAAA...............A....................................",
    "..................A..................AA.............bcaaaabb.......a..ca.cbc........b..................c..............................................................................................AAAAA.....C....B.AAAAA...............A....................................",
    "...................A.................AA.............bcaaaabb.......a..ca.cbc........b..................c..............................................................................................AAAAA.....C....B.AAAAA...............A....................................",
    "...................A.................AA.............bcaaaaba.......a..ca.cbc........b..................c..............................................................................................AAAAA.....C....B.AAAAA...............A....................................",
    "....................A................AA.............bcaaaaba.......a..ca.cbc........b..................c..............................................................................................AAAAA.....C....B.AAAAA...............A....................................",
    "....................A................AA.............ccaaaaba.......a..ca.cbc........b..................c..............................................................................................AAAAA.....C....B.AAAAA...............A....................................",
    ".....................A...............AA.............ccaaaaba.......a..ca.cbc........b..................c..............................................................................................AAAAA.....C....B.AAAAA...............A....................................",
    ".....................A...............AA.............acaaaaba.......a..ca.cbc........b..................c..............................................................................................AAAAA.....C....B.AAAAA...............A....................................",
    "......................A..............AA.............acaaaaba.......a..ca.cbc........b..................c..............................................................................................AAAAA.....C....B.AAAAA...............A....................................",
    "......................A..............AA.............acaaaaba.......a..cb.cbc........b..................c..............................................................................................AAAAA.....C....B.AAAAA...............A....................................",
    ".......................A.............AA.............acaaaaba.......a..cb.cbc........b..................c..............................................................................................AAAAA.....C....B.AAAAA...............A....................................",
    ".......................A.............AA.............acabaaba.......a..cb.cbc........b..................c..............................................................................................AAAAA.....C....B.AAAAA...............A....................................",
    ".....................................AAA............acabaaba.......a..cb.cbc........b..................c..............................................................................................AAAAA.....C....B.AAAAA...............A....................................",
    ".....................................AAA.............cabaaba.......aa.cb.cbc........b..................c..............................................................................................AAAAA.....C....B.AAAAA...............A....................................",
    ".....................................AAA.............cabaaba.......aa.cb.cbc........b..................c..............................................................................................AAAAA.....C....BA.AAAA...............A....................................",
    ".....................................AAA.............cabaaba.......a.acb.cbc........b..................c..............................................................................................AAAAA.....C....BA.AAAA...............A....................................",
    ".....................................AAA.............cabaaba.......a.acb.cbc........b..................c..............................................................................A...............AAAAA.....C....B..AAAA...............A....................................",
    ".....................................AAA.............cabaaba.......a.bcb.cbc........b..................c..............................................................................A...............AAAAA.....C....B..AAAA...............A....................................",
    ".....................................AAA.............cabaaba.......a.bcb.cbc........b..................c..............................................................................A..............A.AAAA.....C....B..AAAA...............A....................................",
    ".....................................AAA.............cabaaca.......a.bcb.cbc........b..................c..............................................................................A..............A.AAAA.....C....B..AAAA...............A....................................",
    ".....................................AAA........A....cabaaca.......a.bcb.cbc........b..................c..............................................................................A................AAAA.....C....B..AAAA...............A....................................",
    ".....................................AAA........A....cabaaca.......a.bcb.abc........b..................c..............................................................................A................AAAA.....C....B..AAAA...............A....................................",
    "................................A....AAA.............cabaaca.......a.bcb.abc........b..................c..............................................................................A................AAAA.....C....B..AAAA...............A....................................",
    "................................A....AAA.............cabcaca.......a.bcb.abc........b..................c..............................................................................A................AAAA.....C....B..AAAA...............A....................................",
    "................................A....AAA.............cabcaca.......a.bcb.abc........b..................c..............................................................................AA................AAA.....C....B..AAAA...............A....................................",
    "................................A....AAA.............cabcaca......a..bcb.abc........b..................c..............................................................................AA................AAA.....C....B..AAAA...............A....................................",
    "................................A....AAA.............cabcaca......a..bcb.abc........b..................c...............................................................A..............A.................AAA.....C....B..AAAA...............A....................................",
    "................................A....AAA.............cabcaca......c..bcb.abc........b..................c...............................................................A..............A.................AAA.....C....B..AAAA...............A....................................",
    "................................A....AAA.............cabcaca......c..bcb.abc........b..................c...............................................................A..............A.................A.AA....C....B..AAAA...............A....................................",
    "................................A....AAA.............cabcaca......c..bbb.abc........b..................c...............................................................A..............A.................A.AA....C....B..AAAA...............A....................................",
    "................................A....AAA.............cabcaca......c..bbb.abc........b..................c...............................................A..............................A.................A.AA....C....B..AAAA...............A....................................",
    "................................A....AAA.............cabcaca......c..bcb.abc........b..................c...............................................A..............................A.................A.AA....C....B..AAAA...............A....................................",
    "................................A....AAA.............cabcaca......c..bcb.abc........b..................c...............................A..............................................A.................A.AA....C....B..AAAA...............A....................................",
    "................................A....AAA.............cabcaca......c..bcb.aba........b..................c...............................A..............................................A.................A.AA....C....B..AAAA...............A....................................",
    "................................A....AAA.............cabcaca......c..bcb.aba........b..................c...............A..............................................................A.................A.AA....C....B..AAAA...............A....................................",
    "................................A....AAA.............cabcaca......c..bcb.cba........b..................c...............A..............................................................A.................A.AA....C....B..AAAA...............A....................................",
    "................................A....AAA.............cabcaca......c..bcbAcba........b..................c..............................................................................A.................A.AA....C....B..AAAA...............A....................................",
    "................................A....AAA.............cabcaca......c..bcbAcb.........b......a...........c..............................................................................A.................A.AA....C....B..AAAA...............A....................................",
    "................................A....AAAA............cabcaca......c..bcb.cb.........b......a...........c..............................................................................A.................A.AA....C....B..AAAA...............A....................................",
    "................................A....AAAA............cabcaca......c..bcc.cb.........b......a...........c..............................................................................A.................A.AA....C....B..AAAA...............A....................................",
    "................................A....AAAA............cabcaca......c..bcc.cb.........b......a...........c..............................................................................A...A.............A.AA....C....B..AA.A...............A....................................",
    "................................A....AAAA............cabcaba......c..bcc.cb.........b......a...........c..............................................................................A...A.............A.AA....C....B..AA.A...............A....................................",
    ".....................................AAAA.......A....cabcaba......c..bcc.cb.........b......a...........c..............................................................................A...A.............A.AA....C....B..AA.A...............A....................................",
    ".....................................AAAA.......A....cabcaba......c..bcc.cb.........b......a...........a..............................................................................A...A.............A.AA....C....B..AA.A...............A....................................",
    ".....................................AAAA............cabcaba....A.c..bcc.cb.........b......a...........a..............................................................................A...A.............A.AA....C....B..AA.A...............A....................................",
    ".....................................AAAA............cabcaba....A.b..bcc.cb.........b......a...........a..............................................................................A...A.............A.AA....C....B..AA.A...............A....................................",
    ".....................................AAAA.......A....cabcaba......b..bcc.cb.........b......a...........a..............................................................................A...A.............A.AA....C....B..AA.A...............A....................................",
    ".....................................AAAA.......A....cabcaba......b..bcc.bb.........b......a...........a..............................................................................A...A.............A.AA....C....B..AA.A...............A....................................",
    ".....................................AAAA.......A....cabcaba......b..bcc.bb.........b......a...........a..................................................................A...........A...A.............A..A....C....B..AA.A...............A....................................",
    ".....................................AAAA.......A....cabcaba......b..bcc.bc.........b......a...........a..................................................................A...........A...A.............A..A....C....B..AA.A...............A....................................",
    ".....................................AAAA............cabcaba....A.b..bcc.bc.........b......a...........a..................................................................A...........A...A.............A..A....C....B..AA.A...............A....................................",
    ".....................................AAAA............cabcaba....A.b..bcc.ac.........b......a...........a..................................................................A...........A...A.............A..A....C....B..AA.A...............A....................................",
    ".....................................AAAA.......A....cabcaba......b..bcc.ac.........b......a...........a..................................................................A...........A...A.............A..A....C....B..AA.A...............A....................................",
    ".....................................AAAA.......A....cabcabb......b..bcc.ac.........b......a...........a..................................................................A...........A...A.............A..A....C....B..AA.A...............A....................................",
    ".....................................AAAA.......A....cabcabb......b..bcc.ac.........b......a...........a..................................................................A...........A...A.............A..A....A....B..AA.A...............A....................................",
    ".....................................AAAA.......A....cabbabb......b..bcc.ac.........b......a...........a..................................................................A...........A...A.............A..A....A....B..AA.A...............A....................................",
    ".....................................AAAA............cabbabb....A.b..bcc.ac.........b......a...........a..................................................................A...........A...A.............A..A....A....B..AA.A...............A....................................",
    ".....................................AAAA............cabbabb....A.b..bcb.ac.........b......a...........a..................................................................A...........A...A.............A..A....A....B..AA.A...............A....................................",
    ".....................................AAAA............cabbabb....A.b..bcb.ac.........b......a...........a..................................................................A...........A...AA............A..A....A....B..AA.................A....................................",
    ".....................................AAAA............cabbabb....A.b..bcb.ac.........b......a..........a...................................................................A...........A...AA............A..A....A....B..AA.................A....................................",
    ".....................................AAAA............cabbabb....A.b..bcb.ac.........b......a..........a...................................................................A..........A....AA............A..A....A....B..AA.................A....................................",
    ".....................................AAAA............cabbabb....A.b..bcb.cc.........b......a..........a...................................................................A..........A....AA............A..A....A....B..AA.................A....................................",
    ".....................................AAAA............cabbabb....A.b..bcb.cc.........b......a..........a...................................................................A.........A.....AA............A..A....A....B..AA.................A....................................",
    ".....................................AAAA............babbabb....A.b..bcb.cc.........b......a..........a...................................................................A.........A.....AA............A..A....A....B..AA.................A....................................",
    ".....................................AAAA............babbabb....A.b..bcb.cc.........b......a..........a.............................................................A.....A...............AA............A..A....A....B..AA.................A....................................",
    ".....................................AAAA............babbaab....A.b..bcb.cc.........b......a..........a.............................................................A.....A...............AA............A..A....A....B..AA.................A....................................",
    ".....................................AAAA............babbaab....A.b..bcb.cc.........b......a..........a.............................................................A.....A................AA...........A..A....A....B..AA.................A....................................",
    ".....................................AAAA............bacbaab....A.b..bcb.cc.........b......a..........a.............................................................A.....A................AA...........A..A....A....B..AA.................A....................................",
    ".....................................AAAA............bacbaab....A.b..bcb.cc.........b......a..........a.............................................................A.....A................AC...........A..A....A....B..AA.................A....................................",
    ".....................................AAAA............bacbaab....A.b..bcb.cc.........b......b..........a.............................................................A.....A................AC...........A..A....A....B..AA.................A....................................",
    ".....................................AAAA...A........bacbaab....A.b..bcb.cc.........b......b..........a.............................................................A.....A.................C...........A..A....A....B..AA.................A....................................",
    ".....................................AAAA...A........baccaab....A.b..bcb.cc.........b......b..........a.............................................................A.....A.................C...........A..A....A....B..AA.................A....................................",
    ".....................................AAAA..A.........baccaab....A.b..bcb.cc.........b......b..........a.............................................................A.....A.................C...........A..A....A....B..AA.................A....................................",
    ".....................................AAAA..A.........baccaab....A.b..bcb.cc.........b......b..........b.............................................................A.....A.................C...........A..A....A....B..AA.................A....................................",
    ".....................................AAAA.A..........baccaab....A.b..bcb.cc.........b......b..........b.............................................................A.....A.................C...........A..A....A....B..AA.................A....................................",
    ".....................................AAAA.A..........bcccaab....A.b..bcb.cc.........b......b..........b.............................................................A.....A.................C...........A..A....A....B..AA.................A....................................",
    ".....................................AAAA.A..........bcccaab....A.b..bcb.cc.........b......b..........b.............................................................A.....A................AC...........A.......A....B..AA.................A....................................",
    ".....................................AAAA.A..........bcccaab....A.a..bcb.cc.........b......b..........b.............................................................A.....A................AC...........A.......A....B..AA.................A....................................",
    "............................A........AAAA.A..........bcccaab....A.a..bcb.cc.........b......b..........b.............................................................A.....A.................C...........A.......A....B..AA.................A....................................",
    "............................A........AAAA.A..........bcccaab....A.c..bcb.cc.........b......b..........b.............................................................A.....A.................C...........A.......A....B..AA.................A....................................",
    "...........................A.........AAAA.A..........bcccaab....A.c..bcb.cc.........b......b..........b.............................................................A.....A.................C...........A.......A....B..AA.................A....................................",
    "...........................A.........AAAA.A..........bcacaab....A.c..bcb.cc.........b......b..........b.............................................................A.....A.................C...........A.......A....B..AA.................A....................................",
    "..........................A..........AAAA.A..........bcacaab....A.c..bcb.cc.........b......b..........b.............................................................A.....A.................C...........A.......A....B..AA.................A....................................",
    "..........................A..........AAAA.A..........bcccaab....A.c..bcb.cc.........b......b..........b.............................................................A.....A.................C...........A.......A....B..AA.................A....................................",
    ".........................A...........AAAA.A..........bcccaab....A.c..bcb.cc.........b......b..........b.............................................................A.....A.................C...........A.......A....B..AA.................A....................................",
    ".........................A...........AAAA.A..........bcccaab....A.c..bcb.ca.........b......b..........b.............................................................A.....A.................C...........A.......A....B..AA.................A....................................",
    ".....................................AAAAAA..........bcccaab....A.c..bcb.ca.........b......b..........b.............................................................A.....A.................C...........A.......A....B..AA.................A...................................."
  ],
  "moves": [
    {
      "player": "circle",
      "move": {
        "action": "push",
        "from": [
          4,
          12
        ],
        "to": [
          4,
          13
        ],
        "pushed_to": [
          4,
          14
        ]
      },
      "state_index": 0,
      "timestamp": 1763142238.0465033
    },
    {
      "player": "square",
      "move": {
        "action": "flip",
        "from": [
          9,
          4
        ],
        "orientation": "horizontal"
      },
      "state_index": 1,
      "timestamp": 1763142238.6681178
    },
    {
      "player": "circle",
      "move": {
        "action": "flip",
        "from": [
          5,
          13
        ],
        "to": [
          0,
          0
        ],
        "orientation": "horizontal"
      },
      "state_index": 2,
      "timestamp": 1763142241.8220325
    },
    {
      "player": "square",
      "move": {
        "action": "flip",
        "from": [
          10,
          4
        ],
        "orientation": "vertical"
      },
      "state_index": 3,
      "timestamp": 1763142242.4576335
    },
    {
      "player": "circle",
      "move": {
        "action": "move",
        "from": [
          4,
          13
        ],
        "to": [
          0,
          13
        ]
      },
      "state_index": 4,
      "timestamp": 1763142243.3367448
    },
    {
      "player": "square",
      "move": {
        "action": "flip",
        "from": [
          11,
          3
        ],
        "orientation": "vertical"
      },
      "state_index": 5,
      "timestamp": 1763142243.9765646
    },
    {
      "player": "circle",
      "move": {
        "action": "push",
        "from": [
          11,
          12
        ],
        "to": [
          11,
          13
        ],
        "pushed_to": [
          11,
          14
        ]
      },
      "state_index": 6,
      "timestamp": 1763142244.8508918
    },
    {
      "player": "square",
      "move": {
        "action": "move",
        "from": [
          4,
          4
        ],
        "to": [
          4,
          5
        ]
      },
      "state_index": 7,
      "timestamp": 1763142245.499767
    },
    {
      "player": "circle",
      "move": {
        "action": "flip",
        "from": [
          0,
          13
        ],
        "to": [
          0,
          0
        ],
        "orientation": "vertical"
      },
      "state_index": 8,
      "timestamp": 1763142246.3619285
    },
    {
      "player": "square",
      "move": {
        "action": "flip",
        "from": [
          11,
          3
        ]
      },
      "state_index": 9,
      "timestamp": 1763142247.0158188
    },
    {
      "player": "circle",
      "move": {
        "action": "move",
        "from": [
          5,
          12
        ],
        "to": [
          0,
          2
        ]
      },
      "state_index": 10,
      "timestamp": 1763142248.7448545
    },
    {
      "player": "square",
      "move": {
        "action": "rotate",
        "from": [
          9,
          4
        ]
      },
      "state_index": 11,
      "timestamp": 1763142249.5315382
    },
    {
      "player": "circle",
      "move": {
        "action": "move",
        "from": [
          0,
          2
        ],
        "to": [
          1,
          2
        ]
      },
      "state_index": 12,
      "timestamp": 1763142251.073124
    },
    {
      "player": "square",
      "move": {
        "action": "flip",
        "from": [
          10,
          3
        ],
        "orientation": "horizontal"
      },
      "state_index": 13,
      "timestamp": 1763142252.0457435
    },
    {
      "player": "circle",
      "move": {
        "action": "move",
        "from": [
          1,
          2
        ],
        "to": [
          2,
          2
        ]
      },
      "state_index": 14,
      "timestamp": 1763142253.2371209
    },
    {
      "player": "square",
      "move": {
        "action": "flip",
        "from": [
          4,
          3
        ],
        "orientation": "horizontal"
      },
      "state_index": 15,
      "timestamp": 1763142253.5623996
    },
    {
      "player": "circle",
      "move": {
        "action": "move",
        "from": [
          2,
          2
        ],
        "to": [
          3,
          2
        ]
      },
      "state_index": 16,
      "timestamp": 1763142254.5083764
    },
    {
      "player": "square",
      "move": {
        "action": "flip",
        "from": [
          11,
          4
        ],
        "orientation": "horizontal"
      },
      "state_index": 17,
      "timestamp": 1763142255.0752027
    },
    {
      "player": "circle",
      "move": {
        "action": "move",
        "from": [
          3,
          2
        ],
        "to": [
          4,
          2
        ]
      },
      "state_index": 18,
      "timestamp": 1763142256.7833524
    },
    {
      "player": "square",
      "move": {
        "action": "flip",
        "from": [
          9,
          3
        ],
        "orientation": "horizontal"
      },
      "state_index": 19,
      "timestamp": 1763142257.5974667
    },
    {
      "player": "circle",
      "move": {
        "action": "move",
        "from": [
          4,
          2
        ],
        "to": [
          5,
          2
        ]
      },
      "state_index": 20,
      "timestamp": 1763142258.9641533
    },
    {
      "player": "square",
      "move": {
        "action": "flip",
        "from": [
          6,
          4
        ],
        "orientation": "vertical"
      },
      "state_index": 21,
      "timestamp": 1763142259.120404
    },
    {
      "player": "circle",
      "move": {
        "action": "move",
        "from": [
          6,
          13
        ],
        "to": [
          0,
          1
        ]
      },
      "state_index": 22,
      "timestamp": 1763142260.8481185
    },
    {
      "player": "square",
      "move": {
        "action": "rotate",
        "from": [
          11,
          4
        ]
      },
      "state_index": 23,
      "timestamp": 1763142261.6357315
    },
    {
      "player": "circle",
      "move": {
        "action": "move",
        "from": [
          0,
          1
        ],
        "to": [
          1,
          1
        ]
      },
      "state_index": 24,
      "timestamp": 1763142263.0337412
    },
    {
      "player": "square",
      "move": {
        "action": "move",
        "from": [
          8,
          4
        ],
        "to": [
          8,
          5
        ]
      },
      "state_index": 25,
      "timestamp": 1763142263.1498442
    },
    {
      "player": "circle",
      "move": {
        "action": "move",
        "from": [
          1,
          1
        ],
        "to": [
          2,
          1
        ]
      },
      "state_index": 26,
      "timestamp": 1763142264.2765484
    },
    {
      "player": "square",
      "move": {
        "action": "flip",
        "from": [
          4,
          5
        ],
        "orientation": "horizontal"
      },
      "state_index": 27,
      "timestamp": 1763142264.6664815
    },
    {
      "player": "circle",
      "move": {
        "action": "move",
        "from": [
          2,
          1
        ],
        "to": [
          3,
          1
        ]
      },
      "state_index": 28,
      "timestamp": 1763142265.593384
    },
    {
      "player": "square",
      "move": {
        "action": "flip",
        "from": [
          9,
          3
        ]
      },
      "state_index": 29,
      "timestamp": 1763142266.181014
    },
    {
      "player": "circle",
      "move": {
        "action": "move",
        "from": [
          3,
          1
        ],
        "to": [
          4,
          1
        ]
      },
      "state_index": 30,
      "timestamp": 1763142267.798493
    },
    {
      "player": "square",
      "move": {
        "action": "flip",
        "from": [
          11,
          3
        ],
        "orientation": "horizontal"
      },
      "state_index": 31,
      "timestamp": 1763142268.6982272
    },
    {
      "player": "circle",
      "move": {
        "action": "move",
        "from": [
          4,
          1
        ],
        "to": [
          5,
          1
        ]
      },
      "state_index": 32,
      "timestamp": 1763142269.9778886
    },
    {
      "player": "square",
      "move": {
        "action": "move",
        "from": [
          8,
          5
        ],
        "to": [
          7,
          5
        ]
      },
      "state_index": 33,
      "timestamp": 1763142270.2203517
    },
    {
      "player": "circle",
      "move": {
        "action": "move",
        "from": [
          5,
          1
        ],
        "to": [
          6,
          1
        ]
      },
      "state_index": 34,
      "timestamp": 1763142271.1301644
    },
    {
      "player": "square",
      "move": {
        "action": "move",
        "from": [
          5,
          4
        ],
        "to": [
          4,
          4
        ]
      },
      "state_index": 35,
      "timestamp": 1763142271.7358027
    },
    {
      "player": "circle",
      "move": {
        "action": "move",
        "from": [
          6,
          1
        ],
        "to": [
          6,
          2
        ]
      },
      "state_index": 36,
      "timestamp": 1763142273.6489782
    },
    {
      "player": "square",
      "move": {
        "action": "flip",
        "from": [
          5,
          3
        ],
        "orientation": "vertical"
      },
      "state_index": 37,
      "timestamp": 1763142276.4776382
    },
    {
      "player": "circle",
      "move": {
        "action": "move",
        "from": [
          4,
          14
        ],
        "to": [
          4,
          13
        ]
      },
      "state_index": 38,
      "timestamp": 1763142279.8562999
    },
    {
      "player": "square",
      "move": {
        "action": "move",
        "from": [
          7,
          5
        ],
        "to": [
          7,
          6
        ]
      },
      "state_index": 39,
      "timestamp": 1763142279.9998167
    },
    {
      "player": "circle",
      "move": {
        "action": "move",
        "from": [
          4,
          13
        ],
        "to": [
          0,
          1
        ]
      },
      "state_index": 40,
      "timestamp": 1763142283.0199158
    },
    {
      "player": "square",
      "move": {
        "action": "rotate",
        "from": [
          10,
          4
        ]
      },
      "state_index": 41,
      "timestamp": 1763142283.525092
    },
    {
      "player": "circle",
      "move": {
        "action": "move",
        "from": [
          0,
          1
        ],
        "to": [
          1,
          1
        ]
      },
      "state_index": 42,
      "timestamp": 1763142285.3205314
    },
    {
      "player": "square",
      "move": {
        "action": "flip",
        "from": [
          7,
          6
        ],
        "orientation": "vertical"
      },
      "state_index": 43,
      "timestamp": 1763142286.0632524
    },
    {
      "player": "circle",
      "move": {
        "action": "move",
        "from": [
          1,
          1
        ],
        "to": [
          2,
          1
        ]
      },
      "state_index": 44,
      "timestamp": 1763142287.5260792
    },
    {
      "player": "square",
      "move": {
        "action": "move",
        "from": [
          4,
          4
        ],
        "to": [
          3,
          4
        ]
      },
      "state_index": 45,
      "timestamp": 1763142287.5939536
    },
    {
      "player": "circle",
      "move": {
        "action": "move",
        "from": [
          2,
          1
        ],
        "to": [
          3,
          1
        ]
      },
      "state_index": 46,
      "timestamp": 1763142288.670169
    },
    {
      "player": "square",
      "move": {
        "action": "flip",
        "from": [
          11,
          3
        ]
      },
      "state_index": 47,
      "timestamp": 1763142289.1061864
    },
    {
      "player": "circle",
      "move": {
        "action": "move",
        "from": [
          3,
          1
        ],
        "to": [
          4,
          1
        ]
      },
      "state_index": 48,
      "timestamp": 1763142289.9535923
    },
    {
      "player": "square",
      "move": {
        "action": "rotate",
        "from": [
          4,
          3
        ]
      },
      "state_index": 49,
      "timestamp": 1763142290.6250134
    },
    {
      "player": "circle",
      "move": {
        "action": "move",
        "from": [
          4,
          1
        ],
        "to": [
          5,
          1
        ]
      },
      "state_index": 50,
      "timestamp": 1763142292.1792383
    },
    {
      "player": "square",
      "move": {
        "action": "flip",
        "from": [
          4,
          3
        ]
      },
      "state_index": 51,
      "timestamp": 1763142293.1473536
    },
    {
      "player": "circle",
      "move": {
        "action": "move",
        "from": [
          5,
          1
        ],
        "to": [
          6,
          1
        ]
      },
      "state_index": 52,
      "timestamp": 1763142294.5438206
    },
    {
      "player": "square",
      "move": {
        "action": "flip",
        "from": [
          7,
          4
        ],
        "orientation": "horizontal"
      },
      "state_index": 53,
      "timestamp": 1763142294.681553
    },
    {
      "player": "circle",
      "move": {
        "action": "move",
        "from": [
          6,
          1
        ],
        "to": [
          7,
          1
        ]
      },
      "state_index": 54,
      "timestamp": 1763142296.0143988
    },
    {
      "player": "square",
      "move": {
        "action": "flip",
        "from": [
          7,
          3
        ],
        "orientation": "horizontal"
      },
      "state_index": 55,
      "timestamp": 1763142296.1995065
    },
    {
      "player": "circle",
      "move": {
        "action": "move",
        "from": [
          7,
          1
        ],
        "to": [
          7,
          2
        ]
      },
      "state_index": 56,
      "timestamp": 1763142298.1466315
    },
    {
      "player": "square",
      "move": {
        "action": "move",
        "from": [
          4,
          3
        ],
        "to": [
          4,
          4
        ]
      },
      "state_index": 57,
      "timestamp": 1763142298.7217605
    },
    {
      "player": "circle",
      "move": {
        "action": "move",
        "from": [
          7,
          13
        ],
        "to": [
          6,
          13
        ]
      },
      "state_index": 58,
      "timestamp": 1763142302.6785827
    },
    {
      "player": "square",
      "move": {
        "action": "move",
        "from": [
          4,
          4
        ],
        "to": [
          5,
          4
        ]
      },
      "state_index": 59,
      "timestamp": 1763142303.2531438
    },
    {
      "player": "circle",
      "move": {
        "action": "push",
        "from": [
          6,
          13
        ],
        "to": [
          6,
          12
        ],
        "pushed_to": [
          6,
          11
        ]
      },
      "state_index": 60,
      "timestamp": 1763142310.9420202
    },
    {
      "player": "square",
      "move": {
        "action": "flip",
        "from": [
          5,
          4
        ],
        "orientation": "horizontal"
      },
      "state_index": 61,
      "timestamp": 1763142311.0466526
    },
    {
      "player": "circle",
      "move": {
        "action": "move",
        "from": [
          6,
          12
        ],
        "to": [
          5,
          12
        ]
      },
      "state_index": 62,
      "timestamp": 1763142313.5971756
    },
    {
      "player": "square",
      "move": {
        "action": "rotate",
        "from": [
          10,
          3
        ]
      },
      "state_index": 63,
      "timestamp": 1763142314.5703895
    },
    {
      "player": "circle",
      "move": {
        "action": "move",
        "from": [
          5,
          12
        ],
        "to": [
          0,
          3
        ]
      },
      "state_index": 64,
      "timestamp": 1763142317.3563716
    },
    {
      "player": "square",
      "move": {
        "action": "flip",
        "from": [
          9,
          4
        ]
      },
      "state_index": 65,
      "timestamp": 1763142318.097239
    },
    {
      "player": "circle",
      "move": {
        "action": "move",
        "from": [
          0,
          3
        ],
        "to": [
          0,
          2
        ]
      },
      "state_index": 66,
      "timestamp": 1763142320.4312963
    },
    {
      "player": "square",
      "move": {
        "action": "flip",
        "from": [
          8,
          3
        ],
        "orientation": "vertical"
      },
      "state_index": 67,
      "timestamp": 1763142320.621784
    },
    {
      "player": "circle",
      "move": {
        "action": "move",
        "from": [
          7,
          12
        ],
        "to": [
          7,
          11
        ]
      },
      "state_index": 68,
      "timestamp": 1763142321.6721704
    },
    {
      "player": "square",
      "move": {
        "action": "move",
        "from": [
          3,
          4
        ],
        "to": [
          2,
          4
        ]
      },
      "state_index": 69,
      "timestamp": 1763142322.1415963
    },
    {
      "player": "circle",
      "move": {
        "action": "move",
        "from": [
          7,
          11
        ],
        "to": [
          7,
          10
        ]
      },
      "state_index": 70,
      "timestamp": 1763142323.0015738
    },
    {
      "player": "square",
      "move": {
        "action": "flip",
        "from": [
          2,
          4
        ],
        "orientation": "vertical"
      },
      "state_index": 71,
      "timestamp": 1763142323.6624343
    },
    {
      "player": "circle",
      "move": {
        "action": "push",
        "from": [
          9,
          12
        ],
        "to": [
          10,
          12
        ],
        "pushed_to": [
          11,
          12
        ]
      },
      "state_index": 72,
      "timestamp": 1763142325.485792
    },
    {
      "player": "square",
      "move": {
        "action": "rotate",
        "from": [
          6,
          4
        ]
      },
      "state_index": 73,
      "timestamp": 1763142326.1798408
    },
    {
      "player": "circle",
      "move": {
        "action": "move",
        "from": [
          7,
          10
        ],
        "to": [
          7,
          9
        ]
      },
      "state_index": 74,
      "timestamp": 1763142328.2120824
    },
    {
      "player": "square",
      "move": {
        "action": "rotate",
        "from": [
          6,
          4
        ]
      },
      "state_index": 75,
      "timestamp": 1763142328.702764
    },
    {
      "player": "circle",
      "move": {
        "action": "move",
        "from": [
          7,
          9
        ],
        "to": [
          7,
          8
        ]
      },
      "state_index": 76,
      "timestamp": 1763142329.5732465
    },
    {
      "player": "square",
      "move": {
        "action": "flip",
        "from": [
          11,
          4
        ]
      },
      "state_index": 77,
      "timestamp": 1763142330.2213802
    },
    {
      "player": "circle",
      "move": {
        "action": "move",
        "from": [
          7,
          8
        ],
        "to": [
          7,
          7
        ]
      },
      "state_index": 78,
      "timestamp": 1763142331.9436102
    },
    {
      "player": "square",
      "move": {
        "action": "flip",
        "from": [
          9,
          4
        ],
        "orientation": "vertical"
      },
      "state_index": 79,
      "timestamp": 1763142332.7435594
    },
    {
      "player": "circle",
      "move": {
        "action": "move",
        "from": [
          7,
          7
        ],
        "to": [
          8,
          4
        ]
      },
      "state_index": 80,
      "timestamp": 1763142334.6041334
    },
    {
      "player": "square",
      "move": {
        "action": "move",
        "from": [
          11,
          4
        ],
        "to": [
          11,
          5
        ]
      },
      "state_index": 81,
      "timestamp": 1763142335.2664566
    },
    {
      "player": "circle",
      "move": {
        "action": "move",
        "from": [
          8,
          4
        ],
        "to": [
          8,
          2
        ]
      },
      "state_index": 82,
      "timestamp": 1763142338.729031
    },
    {
      "player": "square",
      "move": {
        "action": "rotate",
        "from": [
          7,
          4
        ]
      },
      "state_index": 83,
      "timestamp": 1763142338.790466
    },
    {
      "player": "circle",
      "move": {
        "action": "push",
        "from": [
          10,
          13
        ],
        "to": [
          10,
          12
        ],
        "pushed_to": [
          10,
          11
        ]
      },
      "state_index": 84,
      "timestamp": 1763142340.3611372
    },
    {
      "player": "square",
      "move": {
        "action": "rotate",
        "from": [
          10,
          3
        ]
      },
      "state_index": 85,
      "timestamp": 1763142341.3121018
    },
    {
      "player": "circle",
      "move": {
        "action": "move",
        "from": [
          0,
          2
        ],
        "to": [
          0,
          3
        ]
      },
      "state_index": 86,
      "timestamp": 1763142345.538779
    },
    {
      "player": "square",
      "move": {
        "action": "flip",
        "from": [
          7,
          6
        ]
      },
      "state_index": 87,
      "timestamp": 1763142346.091897
    },
    {
      "player": "circle",
      "move": {
        "action": "move",
        "from": [
          0,
          3
        ],
        "to": [
          0,
          4
        ]
      },
      "state_index": 88,
      "timestamp": 1763142350.163763
    },
    {
      "player": "square",
      "move": {
        "action": "rotate",
        "from": [
          2,
          4
        ]
      },
      "state_index": 89,
      "timestamp": 1763142350.6194506
    },
    {
      "player": "circle",
      "move": {
        "action": "move",
        "from": [
          0,
          4
        ],
        "to": [
          0,
          3
        ]
      },
      "state_index": 90,
      "timestamp": 1763142353.2505271
    },
    {
      "player": "square",
      "move": {
        "action": "rotate",
        "from": [
          9,
          4
        ]
      },
      "state_index": 91,
      "timestamp": 1763142354.133776
    },
    {
      "player": "circle",
      "move": {
        "action": "push",
        "from": [
          10,
          12
        ],
        "to": [
          10,
          11
        ],
        "pushed_to": [
          10,
          10
        ]
      },
      "state_index": 92,
      "timestamp": 1763142357.0443525
    },
    {
      "player": "square",
      "move": {
        "action": "rotate",
        "from": [
          10,
          4
        ]
      },
      "state_index": 93,
      "timestamp": 1763142357.6564448
    },
    {
      "player": "circle",
      "move": {
        "action": "move",
        "from": [
          0,
          3
        ],
        "to": [
          0,
          4
        ]
      },
      "state_index": 94,
      "timestamp": 1763142360.843923
    },
    {
      "player": "square",
      "move": {
        "action": "flip",
        "from": [
          9,
          4
        ]
      },
      "state_index": 95,
      "timestamp": 1763142361.1825862
    },
    {
      "player": "circle",
      "move": {
        "action": "move",
        "from": [
          0,
          4
        ],
        "to": [
          0,
          3
        ]
      },
      "state_index": 96,
      "timestamp": 1763142363.5206661
    },
    {
      "player": "square",
      "move": {
        "action": "flip",
        "from": [
          11,
          3
        ],
        "orientation": "horizontal"
      },
      "state_index": 97,
      "timestamp": 1763142363.704049
    },
    {
      "player": "circle",
      "move": {
        "action": "flip",
        "from": [
          0,
          13
        ],
        "to": [
          0,
          0
        ],
        "orientation": ""
      },
      "state_index": 98,
      "timestamp": 1763142365.9268618
    },
    {
      "player": "square",
      "move": {
        "action": "rotate",
        "from": [
          8,
          3
        ]
      },
      "state_index": 99,
      "timestamp": 1763142366.2230246
    },
    {
      "player": "circle",
      "move": {
        "action": "move",
        "from": [
          0,
          3
        ],
        "to": [
          0,
          4
        ]
      },
      "state_index": 100,
      "timestamp": 1763142368.6639717
    },
    {
      "player": "square",
      "move": {
        "action": "rotate",
        "from": [
          7,
          4
        ]
      },
      "state_index": 101,
      "timestamp": 1763142368.7450995
    },
    {
      "player": "circle",
      "move": {
        "action": "push",
        "from": [
          11,
          13
        ],
        "to": [
          11,
          12
        ],
        "pushed_to": [
          11,
          11
        ]
      },
      "state_index": 102,
      "timestamp": 1763142370.965039
    },
    {
      "player": "square",
      "move": {
        "action": "move",
        "from": [
          7,
          6
        ],
        "to": [
          6,
          6
        ]
      },
      "state_index": 103,
      "timestamp": 1763142371.2679245
    },
    {
      "player": "circle",
      "move": {
        "action": "move",
        "from": [
          6,
          11
        ],
        "to": [
          5,
          11
        ]
      },
      "state_index": 104,
      "timestamp": 1763142372.9144685
    },
    {
      "player": "square",
      "move": {
        "action": "flip",
        "from": [
          9,
          4
        ],
        "orientation": "vertical"
      },
      "state_index": 105,
      "timestamp": 1763142373.7887888
    },
    {
      "player": "circle",
      "move": {
        "action": "move",
        "from": [
          5,
          11
        ],
        "to": [
          4,
          11
        ]
      },
      "state_index": 106,
      "timestamp": 1763142375.6103425
    },
    {
      "player": "square",
      "move": {
        "action": "rotate",
        "from": [
          5,
          3
        ]
      },
      "state_index": 107,
      "timestamp": 1763142376.310257
    },
    {
      "player": "circle",
      "move": {
        "action": "move",
        "from": [
          4,
          11
        ],
        "to": [
          4,
          10
        ]
      },
      "state_index": 108,
      "timestamp": 1763142381.5447488
    },
    {
      "player": "square",
      "move": {
        "action": "flip",
        "from": [
          10,
          3
        ]
      },
      "state_index": 109,
      "timestamp": 1763142382.084923
    },
    {
      "player": "circle",
      "move": {
        "action": "push",
        "from": [
          10,
          11
        ],
        "to": [
          11,
          11
        ],
        "pushed_to": [
          12,
          11
        ]
      },
      "state_index": 110,
      "timestamp": 1763142384.315126
    },
    {
      "player": "square",
      "move": {
        "action": "rotate",
        "from": [
          7,
          3
        ]
      },
      "state_index": 111,
      "timestamp": 1763142384.6081212
    },
    {
      "player": "circle",
      "move": {
        "action": "flip",
        "from": [
          12,
          11
        ],
        "to": [
          0,
          0
        ],
        "orientation": "vertical"
      },
      "state_index": 112,
      "timestamp": 1763142386.954315
    },
    {
      "player": "square",
      "move": {
        "action": "flip",
        "from": [
          11,
          5
        ],
        "orientation": "horizontal"
      },
      "state_index": 113,
      "timestamp": 1763142387.1298363
    },
    {
      "player": "circle",
      "move": {
        "action": "move",
        "from": [
          11,
          11
        ],
        "to": [
          12,
          2
        ]
      },
      "state_index": 114,
      "timestamp": 1763142389.7862127
    },
    {
      "player": "square",
      "move": {
        "action": "rotate",
        "from": [
          8,
          3
        ]
      },
      "state_index": 115,
      "timestamp": 1763142390.6509285
    },
    {
      "player": "circle",
      "move": {
        "action": "move",
        "from": [
          12,
          2
        ],
        "to": [
          11,
          2
        ]
      },
      "state_index": 116,
      "timestamp": 1763142393.075072
    },
    {
      "player": "square",
      "move": {
        "action": "flip",
        "from": [
          6,
          6
        ],
        "orientation": "horizontal"
      },
      "state_index": 117,
      "timestamp": 1763142393.1723254
    },
    {
      "player": "circle",
      "move": {
        "action": "move",
        "from": [
          11,
          2
        ],
        "to": [
          10,
          2
        ]
      },
      "state_index": 118,
      "timestamp": 1763142401.040886
    },
    {
      "player": "square",
      "move": {
        "action": "flip",
        "from": [
          6,
          3
        ],
        "orientation": "vertical"
      },
      "state_index": 119,
      "timestamp": 1763142401.703032
    },
    {
      "player": "circle",
      "move": {
        "action": "move",
        "from": [
          11,
          12
        ],
        "to": [
          11,
          11
        ]
      },
      "state_index": 120,
      "timestamp": 1763142404.5962596
    },
    {
      "player": "square",
      "move": {
        "action": "flip",
        "from": [
          2,
          4
        ]
      },
      "state_index": 121,
      "timestamp": 1763142405.2272167
    },
    {
      "player": "circle",
      "move": {
        "action": "move",
        "from": [
          11,
          11
        ],
        "to": [
          12,
          1
        ]
      },
      "state_index": 122,
      "timestamp": 1763142408.6610425
    },
    {
      "player": "square",
      "move": {
        "action": "flip",
        "from": [
          2,
          4
        ],
        "orientation": "vertical"
      },
      "state_index": 123,
      "timestamp": 1763142408.7532568
    },
    {
      "player": "circle",
      "move": {
        "action": "move",
        "from": [
          12,
          1
        ],
        "to": [
          11,
          1
        ]
      },
      "state_index": 124,
      "timestamp": 1763142410.06045
    },
    {
      "player": "square",
      "move": {
        "action": "flip",
        "from": [
          7,
          3
        ]
      },
      "state_index": 125,
      "timestamp": 1763142410.2727137
    },
    {
      "player": "circle",
      "move": {
        "action": "move",
        "from": [
          11,
          1
        ],
        "to": [
          10,
          1
        ]
      },
      "state_index": 126,
      "timestamp": 1763142411.8967655
    },
    {
      "player": "square",
      "move": {
        "action": "flip",
        "from": [
          7,
          3
        ],
        "orientation": "vertical"
      },
      "state_index": 127,
      "timestamp": 1763142415.0177674
    },
    {
      "player": "circle",
      "move": {
        "action": "move",
        "from": [
          10,
          1
        ],
        "to": [
          9,
          1
        ]
      },
      "state_index": 128,
      "timestamp": 1763142416.5302594
    },
    {
      "player": "square",
      "move": {
        "action": "flip",
        "from": [
          10,
          4
        ]
      },
      "state_index": 129,
      "timestamp": 1763142417.5369623
    },
    {
      "player": "circle",
      "move": {
        "action": "move",
        "from": [
          9,
          1
        ],
        "to": [
          9,
          2
        ]
      },
      "state_index": 130,
      "timestamp": 1763142418.8427694
    }
  ]
}